COPYING.GPL
COPYING.MIT.txt
COPYING.SPL.txt
COPYING.TGPPL.rst
MANIFEST.in
NEWS.rst
README.ed25519.rst
README.rst
_doubleloadtester.cpp
copyright
setup.cfg
setup.py
versioneer.py
misc/aside/test-sha256.cpp
misc/build_helpers/show-tool-versions.py
misc/coding_helpers/python.supp
misc/dependencies/setuptools-0.6c14dev.egg
pycryptopp.egg-info/PKG-INFO
pycryptopp.egg-info/SOURCES.txt
pycryptopp.egg-info/dependency_links.txt
pycryptopp.egg-info/not-zip-safe
pycryptopp.egg-info/requires.txt
pycryptopp.egg-info/stdeb.cfg
pycryptopp.egg-info/top_level.txt
src-cryptopp/Doxyfile
src-cryptopp/GNUmakefile
src-cryptopp/License.txt
src-cryptopp/Readme.txt
src-cryptopp/adhoc.cpp.proto
src-cryptopp/aes.h
src-cryptopp/algebra.cpp
src-cryptopp/algebra.h
src-cryptopp/algparam.cpp
src-cryptopp/algparam.h
src-cryptopp/argnames.h
src-cryptopp/asn.cpp
src-cryptopp/asn.h
src-cryptopp/authenc.h
src-cryptopp/basecode.cpp
src-cryptopp/basecode.h
src-cryptopp/cbcmac.h
src-cryptopp/ccm.h
src-cryptopp/channels.h
src-cryptopp/cmac.h
src-cryptopp/config.h
src-cryptopp/cpu.cpp
src-cryptopp/cpu.h
src-cryptopp/cryptdll.dsp
src-cryptopp/cryptdll.vcproj
src-cryptopp/cryptest.dsp
src-cryptopp/cryptest.dsw
src-cryptopp/cryptest.sln
src-cryptopp/cryptest.vcproj
src-cryptopp/cryptest_bds.bdsgroup
src-cryptopp/cryptest_bds.bdsproj
src-cryptopp/cryptest_bds.bpf
src-cryptopp/cryptlib.cpp
src-cryptopp/cryptlib.dsp
src-cryptopp/cryptlib.h
src-cryptopp/cryptlib.vcproj
src-cryptopp/cryptlib_bds.bdsproj
src-cryptopp/cryptopp.rc
src-cryptopp/des.cpp
src-cryptopp/des.h
src-cryptopp/dessp.cpp
src-cryptopp/dh.h
src-cryptopp/dll.cpp
src-cryptopp/dll.h
src-cryptopp/dlltest.dsp
src-cryptopp/dlltest.vcproj
src-cryptopp/dsa.cpp
src-cryptopp/dsa.h
src-cryptopp/ec2n.cpp
src-cryptopp/ec2n.h
src-cryptopp/eccrypto.cpp
src-cryptopp/eccrypto.h
src-cryptopp/ecp.cpp
src-cryptopp/ecp.h
src-cryptopp/emsa2.h
src-cryptopp/eprecomp.cpp
src-cryptopp/eprecomp.h
src-cryptopp/extraversion.h
src-cryptopp/files.h
src-cryptopp/filters.cpp
src-cryptopp/filters.h
src-cryptopp/fips140.cpp
src-cryptopp/fips140.h
src-cryptopp/fltrimpl.h
src-cryptopp/gcm.h
src-cryptopp/gf2n.cpp
src-cryptopp/gf2n.h
src-cryptopp/gfpcrypt.cpp
src-cryptopp/gfpcrypt.h
src-cryptopp/hex.cpp
