Metadata-Version: 1.1
Name: pycryptopp
Version: 0.7.1.869544967005693312591928092448767568728501330214
Summary: Python wrappers for a few algorithms from the Crypto++ library
Home-page: https://tahoe-lafs.org/trac/pycryptopp
Author: Zooko Wilcox
Author-email: zookog@gmail.com
License: GNU GPL
Platform: UNKNOWN
Classifier: Environment :: Console
Classifier: License :: OSI Approved :: GNU General Public License (GPL)
Classifier: License :: DFSG approved
Classifier: Intended Audience :: Developers
Classifier: Operating System :: Microsoft :: Windows
Classifier: Operating System :: Unix
Classifier: Operating System :: MacOS :: MacOS X
Classifier: Natural Language :: English
Classifier: Programming Language :: C
Classifier: Programming Language :: C++
Classifier: Programming Language :: Python
Classifier: Programming Language :: Python :: 2
Classifier: Programming Language :: Python :: 2.6
Classifier: Programming Language :: Python :: 2.7
Classifier: Topic :: Software Development :: Libraries
